ireton/__init__.py
ireton-0.2.1.dist-info/METADATA
ireton-0.2.1.dist-info/RECORD
ireton-0.2.1.dist-info/WHEEL
ireton-0.2.1.dist-info/top_level.txt
