Metadata-Version: 2.1
Name: ireton
Version: 0.2.1
Summary: testing tools
Home-page: https://github.com/rjsvaljean/python-testing-tools
Author: ratatat
Author-email: ratanjagan@gmail.com
License: MIT
Platform: UNKNOWN
